oil/__init__.py
oil/architectures/__init__.py
oil/architectures/img2img/__init__.py
oil/architectures/img_classifiers/__init__.py
oil/architectures/img_classifiers/densenet.py
oil/architectures/img_classifiers/networkparts.py
oil/architectures/img_classifiers/preresnet.py
oil/architectures/img_classifiers/shake_shake.py
oil/architectures/img_classifiers/smallconv.py
oil/architectures/img_classifiers/transformer.py
oil/architectures/img_classifiers/vgg.py
oil/architectures/img_classifiers/wide_resnet.py
oil/architectures/img_gen/__init__.py
oil/architectures/img_gen/conditionalgan.py
oil/architectures/img_gen/ganBase.py
oil/architectures/img_gen/resnetgan.py
oil/architectures/parts/CoordConv.py
oil/architectures/parts/__init__.py
oil/architectures/parts/antialiasing.py
oil/architectures/parts/attention.py
oil/architectures/parts/blocks.py
oil/architectures/parts/deconv.py
oil/architectures/parts/denseblocks.py
oil/architectures/pointcloud/__init__.py
oil/datasetup/__init__.py
oil/datasetup/augLayers.py
oil/datasetup/camvid.py
oil/datasetup/celeba.py
oil/datasetup/dataloaders.py
oil/datasetup/datasets.py
oil/datasetup/joint_transforms.py
oil/logging/__init__.py
oil/logging/lazyLogger.py
oil/model_trainers/__init__.py
oil/model_trainers/cGan.py
oil/model_trainers/classifier.py
oil/model_trainers/cycleGan.py
oil/model_trainers/gan.py
oil/model_trainers/graphssl.py
oil/model_trainers/piModel.py
oil/model_trainers/segmenter.py
oil/model_trainers/trainer.py
oil/model_trainers/vat.py
oil/recipes/__init__.py
oil/recipes/exampleHyperSearch.py
oil/recipes/simpleTrial.py
oil/recipes/trainCGan.py
oil/recipes/trainGan.py
oil/recipes/trainPi.py
oil/tuning/__init__.py
oil/tuning/args.py
oil/tuning/configGenerator.py
oil/tuning/localGpuExecutor.py
oil/tuning/slurmExecutor.py
oil/tuning/slurm_example.py
oil/tuning/study.py
oil/utils/__init__.py
oil/utils/losses.py
oil/utils/metrics.py
oil/utils/mytqdm.py
oil/utils/optim.py
oil/utils/parallel.py
oil/utils/utils.py
olive_oil_ml-0.1.dist-info/METADATA
olive_oil_ml-0.1.dist-info/WHEEL
olive_oil_ml-0.1.dist-info/top_level.txt
olive_oil_ml-0.1.dist-info/RECORD
