Metadata-Version: 2.1
Name: olive-oil-ml
Version: 0.1
Summary: For slowing down deep learning research
Home-page: UNKNOWN
Author: Marc Finzi
Author-email: maf388@cornell.edu
License: MIT
Platform: UNKNOWN
Requires-Python: >=3.6
Requires-Dist: torch (>=1.2)
Requires-Dist: torchvision
Requires-Dist: pandas
Requires-Dist: numpy
Requires-Dist: matplotlib
Requires-Dist: dill
Requires-Dist: tqdm (>=4.38)
Requires-Dist: natsort
Requires-Dist: sklearn
Requires-Dist: torchcontrib
Provides-Extra: tbx
Requires-Dist: tensorboardX ; extra == 'tbx'
